sagemaker_studio_dataengineering_sessions/__init__.py
sagemaker_studio_dataengineering_sessions/py.typed
sagemaker_studio_dataengineering_sessions/sagemaker_base_session_manager/__init__.py
sagemaker_studio_dataengineering_sessions/sagemaker_base_session_manager/base_connection.py
sagemaker_studio_dataengineering_sessions/sagemaker_base_session_manager/base_debugging_helper.py
sagemaker_studio_dataengineering_sessions/sagemaker_base_session_manager/base_session_manager.py
sagemaker_studio_dataengineering_sessions/sagemaker_base_session_manager/boto3_models/datazone/2018-05-10/service-2.json
sagemaker_studio_dataengineering_sessions/sagemaker_base_session_manager/boto3_models/emr/2009-03-31/service-2.json
sagemaker_studio_dataengineering_sessions/sagemaker_base_session_manager/boto3_models/emr-serverless/2021-07-13/service-2.json
sagemaker_studio_dataengineering_sessions/sagemaker_base_session_manager/boto3_models/glue/2017-03-31/service-2.json
sagemaker_studio_dataengineering_sessions/sagemaker_base_session_manager/boto3_models/sqlworkbench/2024-02-12/service-2.json
sagemaker_studio_dataengineering_sessions/sagemaker_base_session_manager/boto3_models/sso-admin/2020-07-20/service-2.json
sagemaker_studio_dataengineering_sessions/sagemaker_base_session_manager/common/__init__.py
sagemaker_studio_dataengineering_sessions/sagemaker_base_session_manager/common/cache.py
sagemaker_studio_dataengineering_sessions/sagemaker_base_session_manager/common/client_utils.py
sagemaker_studio_dataengineering_sessions/sagemaker_base_session_manager/common/constants.py
sagemaker_studio_dataengineering_sessions/sagemaker_base_session_manager/common/debugging_utils.py
sagemaker_studio_dataengineering_sessions/sagemaker_base_session_manager/common/exceptions.py
sagemaker_studio_dataengineering_sessions/sagemaker_base_session_manager/common/ipython_display.py
sagemaker_studio_dataengineering_sessions/sagemaker_base_session_manager/common/logger_utils.py
sagemaker_studio_dataengineering_sessions-1.3.11.dist-info/METADATA
sagemaker_studio_dataengineering_sessions-1.3.11.dist-info/WHEEL
sagemaker_studio_dataengineering_sessions-1.3.11.dist-info/licenses/LICENSE
sagemaker_studio_dataengineering_sessions-1.3.11.dist-info/licenses/NOTICE
sagemaker_studio_dataengineering_sessions-1.3.11.dist-info/RECORD
