Metadata-Version: 2.4
Name: sagemaker-studio-dataengineering-sessions
Version: 1.3.11
Summary: A python Package to run Spark code in different AWS Compute
Author: Amazon Web Services
Maintainer: sagemaker-unified-studio
License-Expression: Apache-2.0
License-File: LICENSE
License-File: NOTICE
Keywords: AWS,Amazon,Data Engineering,SageMaker,SageMaker Unified Studio
Classifier: License :: OSI Approved :: Apache Software License
Classifier: Programming Language :: Python
Classifier: Programming Language :: Python :: 3
Classifier: Programming Language :: Python :: 3.11
Requires-Python: >=3.11
Requires-Dist: amazon-sagemaker-sql-execution<1,>=0.0.7
Requires-Dist: boto3
Requires-Dist: botocore
Requires-Dist: ipython
Requires-Dist: pandas
Requires-Dist: panel>=1.6.0
Requires-Dist: pyarrow
Requires-Dist: pytest
Requires-Dist: pytest-cov
Requires-Dist: sagemaker-studio-sparkmagic-lib
Requires-Dist: sparkmagic
Requires-Dist: sqlparse>=0.4.0
